odoo/addons/stock_free_quantity/README.rst
odoo/addons/stock_free_quantity/__init__.py
odoo/addons/stock_free_quantity/__manifest__.py
odoo/addons/stock_free_quantity/i18n/fr.po
odoo/addons/stock_free_quantity/i18n/it.po
odoo/addons/stock_free_quantity/i18n/stock_free_quantity.pot
odoo/addons/stock_free_quantity/i18n/tr.po
odoo/addons/stock_free_quantity/models/__init__.py
odoo/addons/stock_free_quantity/models/product_product.py
odoo/addons/stock_free_quantity/models/product_template.py
odoo/addons/stock_free_quantity/readme/CONTRIBUTORS.md
odoo/addons/stock_free_quantity/readme/DESCRIPTION.md
odoo/addons/stock_free_quantity/static/description/icon.png
odoo/addons/stock_free_quantity/static/description/index.html
odoo/addons/stock_free_quantity/tests/__init__.py
odoo/addons/stock_free_quantity/tests/test_template_free_qty.py
odoo/addons/stock_free_quantity/views/product_product_view.xml
odoo/addons/stock_free_quantity/views/product_template_view.xml
odoo/addons/stock_free_quantity/views/stock_quant_view.xml
odoo_addon_stock_free_quantity-18.0.1.1.0.1.dist-info/METADATA
odoo_addon_stock_free_quantity-18.0.1.1.0.1.dist-info/WHEEL
odoo_addon_stock_free_quantity-18.0.1.1.0.1.dist-info/top_level.txt
odoo_addon_stock_free_quantity-18.0.1.1.0.1.dist-info/RECORD
