Metadata-Version: 2.1
Name: odoo-addon-stock_free_quantity
Version: 18.0.1.1.0.1
Requires-Python: >=3.10
Requires-Dist: odoo==18.0.*
Summary: Stock Free Quantity
Home-page: https://github.com/OCA/stock-logistics-availability
License: AGPL-3
Author: Akretion,Odoo Community Association (OCA)
Author-email: support@odoo-community.org
Classifier: Programming Language :: Python
Classifier: Framework :: Odoo
Classifier: Framework :: Odoo :: 18.0
Classifier: License :: OSI Approved :: GNU Affero General Public License v3
Classifier: Development Status :: 5 - Production/Stable
